{
  "metadata": {
    "timestamp": "20251124_213159",
    "simulation_time": "2.39s",
    "result": "failure",
    "screenshot_path": "simulation_screenshots/sim_20251124_213159_final_failure.png"
  },
  "statistics": {
    "simulation_duration": 2.391999999999994,
    "alive_small_agents": 0,
    "total_small_agents": 6,
    "alive_large_agents": 0,
    "total_large_agents": 3,
    "map_id": 7,
    "spawn_times": 11,
    "dead_agents": 36,
    "coverage_percentage": 0.0,
    "victim_rescued": false,
    "obstacles_count": 10,
    "danger_zones_count": 15,
    "explored_safe_count": 70
  },
  "agent_details": {
    "small_agents": [
      {
        "id": 1001,
        "alive": false,
        "energycost": 1.3397280121131478,
        "final_position": [
          205,
          375
        ],
        "trajectory_length": 3,
        "hist_traj": [
          [
            192,
            377
          ],
          [
            195,
            375
          ],
          [
            205,
            375
          ]
        ],
        "explored_cells": 580,
        "has_goal": true,
        "goal_position": [
          215,
          375
        ]
      },
      {
        "id": 1006,
        "alive": false,
        "energycost": 1.7539415744862428,
        "final_position": [
          205,
          385
        ],
        "trajectory_length": 3,
        "hist_traj": [
          [
            192,
            377
          ],
          [
            195,
            375
          ],
          [
            205,
            385
          ]
        ],
        "explored_cells": 580,
        "has_goal": true,
        "goal_position": [
          215,
          395
        ]
      },
      {
        "id": 1002,
        "alive": false,
        "energycost": 17.410795823978624,
        "final_position": [
          205,
          385
        ],
        "trajectory_length": 18,
        "hist_traj": [
          [
            192,
            377
          ],
          [
            195,
            375
          ],
          [
            185,
            375
          ],
          [
            175,
            385
          ],
          [
            165,
            385
          ],
          [
            155,
            395
          ],
          [
            145,
            395
          ],
          [
            135,
            405
          ],
          [
            125,
            405
          ],
          [
            125,
            405
          ],
          [
            135,
            405
          ],
          [
            145,
            405
          ],
          [
            155,
            405
          ],
          [
            165,
            405
          ],
          [
            175,
            395
          ],
          [
            185,
            395
          ],
          [
            195,
            385
          ],
          [
            205,
            385
          ]
        ],
        "explored_cells": 686,
        "has_goal": true,
        "goal_position": [
          215,
          375
        ]
      },
      {
        "id": 1007,
        "alive": false,
        "energycost": 33.967145010082675,
        "final_position": [
          265,
          555
        ],
        "trajectory_length": 31,
        "hist_traj": [
          [
            192,
            377
          ],
          [
            195,
            375
          ],
          [
            205,
            365
          ],
          [
            215,
            365
          ],
          [
            225,
            355
          ],
          [
            235,
            355
          ],
          [
            245,
            345
          ],
          [
            255,
            345
          ],
          [
            255,
            345
          ],
          [
            265,
            355
          ],
          [
            275,
            365
          ],
          [
            285,
            375
          ],
          [
            285,
            385
          ],
          [
            295,
            395
          ],
          [
            295,
            405
          ],
          [
            305,
            415
          ],
          [
            305,
            425
          ],
          [
            315,
            435
          ],
          [
            315,
            445
          ],
          [
            315,
            455
          ],
          [
            325,
            465
          ],
          [
            325,
            465
          ],
          [
            315,
            475
          ],
          [
            305,
            485
          ],
          [
            295,
            495
          ],
          [
            285,
            505
          ],
          [
            285,
            515
          ],
          [
            275,
            525
          ],
          [
            275,
            535
          ],
          [
            265,
            545
          ],
          [
            265,
            555
          ]
        ],
        "explored_cells": 937,
        "has_goal": false,
        "goal_position": null
      },
      {
        "id": 1000,
        "alive": false,
        "energycost": 47.03821282194812,
        "final_position": [
          205,
          435
        ],
        "trajectory_length": 42,
        "hist_traj": [
          [
            192,
            377
          ],
          [
            195,
            375
          ],
          [
            205,
            365
          ],
          [
            205,
            355
          ],
          [
            215,
            345
          ],
          [
            215,
            335
          ],
          [
            215,
            325
          ],
          [
            225,
            315
          ],
          [
            225,
            315
          ],
          [
            215,
            315
          ],
          [
            205,
            315
          ],
          [
            195,
            315
          ],
          [
            185,
            315
          ],
          [
            175,
            315
          ],
          [
            165,
            315
          ],
          [
            155,
            315
          ],
          [
            145,
            315
          ],
          [
            135,
            315
          ],
          [
            125,
            315
          ],
          [
            115,
            315
          ],
          [
            105,
            305
          ],
          [
            95,
            305
          ],
          [
            85,
            295
          ],
          [
            75,
            295
          ],
          [
            65,
            285
          ],
          [
            55,
            285
          ],
          [
            55,
            285
          ],
          [
            65,
            295
          ],
          [
            75,
            305
          ],
          [
            85,
            315
          ],
          [
            95,
            325
          ],
          [
            105,
            335
          ],
          [
            115,
            345
          ],
          [
            125,
            355
          ],
          [
            135,
            365
          ],
          [
            145,
            375
          ],
          [
            155,
            385
          ],
          [
            165,
            395
          ],
          [
            175,
            405
          ],
          [
            185,
            415
          ],
          [
            195,
            425
          ],
          [
            205,
            435
          ]
        ],
        "explored_cells": 951,
        "has_goal": true,
        "goal_position": [
          215,
          445
        ]
      },
      {
        "id": 1010,
        "alive": false,
        "energycost": 22.72450432296339,
        "final_position": [
          365,
          485
        ],
        "trajectory_length": 19,
        "hist_traj": [
          [
            192,
            377
          ],
          [
            195,
            375
          ],
          [
            205,
            365
          ],
          [
            215,
            365
          ],
          [
            225,
            365
          ],
          [
            235,
            365
          ],
          [
            245,
            365
          ],
          [
            255,
            375
          ],
          [
            265,
            385
          ],
          [
            275,
            395
          ],
          [
            285,
            405
          ],
          [
            295,
            415
          ],
          [
            305,
            425
          ],
          [
            315,
            435
          ],
          [
            325,
            445
          ],
          [
            335,
            455
          ],
          [
            345,
            465
          ],
          [
            355,
            475
          ],
          [
            365,
            485
          ]
        ],
        "explored_cells": 1306,
        "has_goal": true,
        "goal_position": [
          375,
          495
        ]
      }
    ],
    "large_agents": [
      {
        "id": 2,
        "alive": false,
        "energycost": 3.5078831489724855,
        "final_position": [
          205,
          385
        ],
        "trajectory_length": 3,
        "hist_traj": [
          [
            192,
            377
          ],
          [
            195,
            375
          ],
          [
            205,
            385
          ]
        ],
        "known_cells": 580,
        "total_cells": 7000,
        "known_percentage": 8.285714285714285,
        "son_agents": [
          1006,
          1007,
          1008
        ]
      },
      {
        "id": 0,
        "alive": false,
        "energycost": 128.27743577067292,
        "final_position": [
          135,
          535
        ],
        "trajectory_length": 62,
        "hist_traj": [
          [
            192,
            377
          ],
          [
            195,
            375
          ],
          [
            185,
            385
          ],
          [
            175,
            395
          ],
          [
            165,
            405
          ],
          [
            165,
            415
          ],
          [
            155,
            425
          ],
          [
            155,
            435
          ],
          [
            155,
            435
          ],
          [
            155,
            425
          ],
          [
            155,
            415
          ],
          [
            155,
            405
          ],
          [
            155,
            395
          ],
          [
            155,
            385
          ],
          [
            155,
            375
          ],
          [
            155,
            365
          ],
          [
            155,
            355
          ],
          [
            155,
            345
          ],
          [
            155,
            335
          ],
          [
            155,
            325
          ],
          [
            155,
            315
          ],
          [
            155,
            305
          ],
          [
            165,
            295
          ],
          [
            165,
            285
          ],
          [
            175,
            275
          ],
          [
            175,
            265
          ],
          [
            185,
            255
          ],
          [
            185,
            245
          ],
          [
            185,
            235
          ],
          [
            195,
            225
          ],
          [
            195,
            225
          ],
          [
            195,
            235
          ],
          [
            195,
            245
          ],
          [
            195,
            255
          ],
          [
            195,
            265
          ],
          [
            195,
            275
          ],
          [
            195,
            285
          ],
          [
            195,
            295
          ],
          [
            195,
            305
          ],
          [
            195,
            315
          ],
          [
            195,
            325
          ],
          [
            195,
            335
          ],
          [
            195,
            345
          ],
          [
            195,
            355
          ],
          [
            195,
            365
          ],
          [
            195,
            375
          ],
          [
            185,
            385
          ],
          [
            185,
            395
          ],
          [
            175,
            405
          ],
          [
            175,
            415
          ],
          [
            165,
            425
          ],
          [
            165,
            435
          ],
          [
            165,
            445
          ],
          [
            155,
            455
          ],
          [
            155,
            465
          ],
          [
            145,
            475
          ],
          [
            145,
            485
          ],
          [
            145,
            495
          ],
          [
            145,
            505
          ],
          [
            145,
            515
          ],
          [
            145,
            525
          ],
          [
            135,
            535
          ]
        ],
        "known_cells": 1961,
        "total_cells": 7000,
        "known_percentage": 28.014285714285712,
        "son_agents": [
          1009,
          1012,
          1013
        ]
      },
      {
        "id": 1,
        "alive": false,
        "energycost": 110.07642564389624,
        "final_position": [
          245,
          555
        ],
        "trajectory_length": 50,
        "hist_traj": [
          [
            192,
            377
          ],
          [
            195,
            375
          ],
          [
            195,
            365
          ],
          [
            195,
            355
          ],
          [
            195,
            345
          ],
          [
            195,
            335
          ],
          [
            195,
            325
          ],
          [
            205,
            315
          ],
          [
            205,
            315
          ],
          [
            195,
            305
          ],
          [
            185,
            295
          ],
          [
            175,
            285
          ],
          [
            165,
            275
          ],
          [
            155,
            265
          ],
          [
            145,
            255
          ],
          [
            135,
            245
          ],
          [
            125,
            235
          ],
          [
            125,
            235
          ],
          [
            125,
            245
          ],
          [
            125,
            255
          ],
          [
            125,
            265
          ],
          [
            125,
            275
          ],
          [
            125,
            285
          ],
          [
            125,
            295
          ],
          [
            135,
            305
          ],
          [
            135,
            315
          ],
          [
            145,
            325
          ],
          [
            145,
            335
          ],
          [
            155,
            345
          ],
          [
            155,
            355
          ],
          [
            155,
            365
          ],
          [
            165,
            375
          ],
          [
            165,
            385
          ],
          [
            175,
            395
          ],
          [
            175,
            405
          ],
          [
            185,
            415
          ],
          [
            185,
            425
          ],
          [
            195,
            435
          ],
          [
            195,
            445
          ],
          [
            205,
            455
          ],
          [
            205,
            465
          ],
          [
            205,
            475
          ],
          [
            215,
            485
          ],
          [
            215,
            495
          ],
          [
            225,
            505
          ],
          [
            225,
            515
          ],
          [
            235,
            525
          ],
          [
            235,
            535
          ],
          [
            245,
            545
          ],
          [
            245,
            555
          ]
        ],
        "known_cells": 2000,
        "total_cells": 7000,
        "known_percentage": 28.57142857142857,
        "son_agents": [
          1003,
          1004,
          1005,
          1011
        ]
      }
    ]
  }
}