{
  "metadata": {
    "timestamp": "20251124_214454",
    "simulation_time": "4.13s",
    "result": "success",
    "screenshot_path": "simulation_screenshots/sim_20251124_214454_final_success.png"
  },
  "statistics": {
    "simulation_duration": 4.128999999999984,
    "alive_small_agents": 7,
    "total_small_agents": 6,
    "alive_large_agents": 1,
    "total_large_agents": 3,
    "map_id": 9,
    "spawn_times": 21,
    "dead_agents": 37,
    "coverage_percentage": 45.72857142857143,
    "victim_rescued": true,
    "obstacles_count": 10,
    "danger_zones_count": 15,
    "explored_safe_count": 70
  },
  "agent_details": {
    "small_agents": [
      {
        "id": 1015,
        "alive": true,
        "energycost": 82.45126002547953,
        "final_position": [
          515,
          85
        ],
        "trajectory_length": 80,
        "hist_traj": [
          [
            602,
            345
          ],
          [
            605,
            345
          ],
          [
            605,
            355
          ],
          [
            605,
            365
          ],
          [
            605,
            375
          ],
          [
            605,
            385
          ],
          [
            605,
            395
          ],
          [
            605,
            405
          ],
          [
            605,
            415
          ],
          [
            605,
            425
          ],
          [
            605,
            435
          ],
          [
            605,
            445
          ],
          [
            605,
            455
          ],
          [
            605,
            465
          ],
          [
            605,
            475
          ],
          [
            605,
            485
          ],
          [
            605,
            495
          ],
          [
            605,
            505
          ],
          [
            605,
            515
          ],
          [
            605,
            525
          ],
          [
            605,
            535
          ],
          [
            605,
            545
          ],
          [
            605,
            555
          ],
          [
            605,
            565
          ],
          [
            605,
            565
          ],
          [
            605,
            555
          ],
          [
            605,
            545
          ],
          [
            605,
            535
          ],
          [
            605,
            525
          ],
          [
            605,
            515
          ],
          [
            605,
            505
          ],
          [
            605,
            495
          ],
          [
            605,
            485
          ],
          [
            605,
            475
          ],
          [
            605,
            465
          ],
          [
            605,
            455
          ],
          [
            605,
            445
          ],
          [
            605,
            435
          ],
          [
            605,
            425
          ],
          [
            605,
            415
          ],
          [
            605,
            405
          ],
          [
            595,
            395
          ],
          [
            595,
            385
          ],
          [
            585,
            375
          ],
          [
            585,
            365
          ],
          [
            575,
            355
          ],
          [
            575,
            345
          ],
          [
            565,
            335
          ],
          [
            565,
            325
          ],
          [
            555,
            315
          ],
          [
            555,
            305
          ],
          [
            555,
            295
          ],
          [
            545,
            285
          ],
          [
            545,
            275
          ],
          [
            535,
            265
          ],
          [
            535,
            255
          ],
          [
            525,
            245
          ],
          [
            525,
            235
          ],
          [
            515,
            225
          ],
          [
            515,
            215
          ],
          [
            505,
            205
          ],
          [
            505,
            195
          ],
          [
            505,
            185
          ],
          [
            495,
            175
          ],
          [
            495,
            165
          ],
          [
            485,
            155
          ],
          [
            485,
            145
          ],
          [
            475,
            135
          ],
          [
            475,
            125
          ],
          [
            465,
            115
          ],
          [
            465,
            105
          ],
          [
            455,
            95
          ],
          [
            455,
            85
          ],
          [
            455,
            85
          ],
          [
            465,
            85
          ],
          [
            475,
            85
          ],
          [
            485,
            85
          ],
          [
            495,
            85
          ],
          [
            505,
            85
          ],
          [
            515,
            85
          ]
        ],
        "explored_cells": 1579,
        "has_goal": true,
        "goal_position": [
          525,
          85
        ]
      },
      {
        "id": 1016,
        "alive": true,
        "energycost": 77.27968715022573,
        "final_position": [
          595,
          205
        ],
        "trajectory_length": 74,
        "hist_traj": [
          [
            602,
            345
          ],
          [
            605,
            345
          ],
          [
            605,
            355
          ],
          [
            605,
            365
          ],
          [
            605,
            375
          ],
          [
            605,
            385
          ],
          [
            605,
            395
          ],
          [
            605,
            405
          ],
          [
            605,
            415
          ],
          [
            605,
            425
          ],
          [
            605,
            435
          ],
          [
            605,
            445
          ],
          [
            605,
            455
          ],
          [
            605,
            465
          ],
          [
            605,
            475
          ],
          [
            605,
            485
          ],
          [
            605,
            495
          ],
          [
            605,
            505
          ],
          [
            605,
            515
          ],
          [
            605,
            525
          ],
          [
            615,
            535
          ],
          [
            615,
            545
          ],
          [
            615,
            555
          ],
          [
            625,
            565
          ],
          [
            625,
            565
          ],
          [
            625,
            555
          ],
          [
            625,
            545
          ],
          [
            625,
            535
          ],
          [
            625,
            525
          ],
          [
            625,
            515
          ],
          [
            625,
            505
          ],
          [
            625,
            495
          ],
          [
            625,
            485
          ],
          [
            625,
            475
          ],
          [
            625,
            465
          ],
          [
            625,
            455
          ],
          [
            625,
            445
          ],
          [
            625,
            435
          ],
          [
            625,
            425
          ],
          [
            625,
            415
          ],
          [
            625,
            405
          ],
          [
            615,
            395
          ],
          [
            605,
            385
          ],
          [
            605,
            375
          ],
          [
            605,
            365
          ],
          [
            605,
            355
          ],
          [
            605,
            345
          ],
          [
            595,
            335
          ],
          [
            585,
            325
          ],
          [
            585,
            315
          ],
          [
            585,
            305
          ],
          [
            585,
            295
          ],
          [
            585,
            285
          ],
          [
            585,
            275
          ],
          [
            585,
            265
          ],
          [
            585,
            255
          ],
          [
            585,
            245
          ],
          [
            585,
            235
          ],
          [
            585,
            225
          ],
          [
            585,
            215
          ],
          [
            595,
            205
          ],
          [
            605,
            195
          ],
          [
            615,
            185
          ],
          [
            625,
            175
          ],
          [
            635,
            165
          ],
          [
            635,
            155
          ],
          [
            645,
            145
          ],
          [
            645,
            145
          ],
          [
            635,
            155
          ],
          [
            625,
            165
          ],
          [
            615,
            175
          ],
          [
            605,
            185
          ],
          [
            605,
            195
          ],
          [
            595,
            205
          ]
        ],
        "explored_cells": 1523,
        "has_goal": true,
        "goal_position": [
          585,
          215
        ]
      },
      {
        "id": 1019,
        "alive": true,
        "energycost": 31.652270152256243,
        "final_position": [
          875,
          395
        ],
        "trajectory_length": 34,
        "hist_traj": [
          [
            602,
            345
          ],
          [
            605,
            345
          ],
          [
            605,
            355
          ],
          [
            605,
            365
          ],
          [
            605,
            375
          ],
          [
            605,
            385
          ],
          [
            615,
            395
          ],
          [
            625,
            395
          ],
          [
            635,
            395
          ],
          [
            645,
            395
          ],
          [
            655,
            395
          ],
          [
            665,
            395
          ],
          [
            675,
            395
          ],
          [
            685,
            395
          ],
          [
            695,
            395
          ],
          [
            705,
            395
          ],
          [
            715,
            395
          ],
          [
            725,
            395
          ],
          [
            735,
            395
          ],
          [
            745,
            395
          ],
          [
            755,
            395
          ],
          [
            765,
            395
          ],
          [
            775,
            395
          ],
          [
            785,
            395
          ],
          [
            795,
            395
          ],
          [
            805,
            395
          ],
          [
            815,
            395
          ],
          [
            815,
            395
          ],
          [
            825,
            395
          ],
          [
            835,
            395
          ],
          [
            845,
            395
          ],
          [
            855,
            395
          ],
          [
            865,
            395
          ],
          [
            875,
            395
          ]
        ],
        "explored_cells": 1969,
        "has_goal": true,
        "goal_position": [
          885,
          395
        ]
      },
      {
        "id": 1020,
        "alive": true,
        "energycost": 33.794405775987194,
        "final_position": [
          855,
          295
        ],
        "trajectory_length": 32,
        "hist_traj": [
          [
            602,
            345
          ],
          [
            605,
            345
          ],
          [
            605,
            355
          ],
          [
            605,
            365
          ],
          [
            605,
            375
          ],
          [
            605,
            385
          ],
          [
            615,
            395
          ],
          [
            625,
            395
          ],
          [
            635,
            395
          ],
          [
            645,
            395
          ],
          [
            655,
            395
          ],
          [
            665,
            395
          ],
          [
            675,
            395
          ],
          [
            685,
            395
          ],
          [
            695,
            395
          ],
          [
            705,
            395
          ],
          [
            715,
            395
          ],
          [
            725,
            385
          ],
          [
            735,
            385
          ],
          [
            745,
            375
          ],
          [
            755,
            375
          ],
          [
            765,
            365
          ],
          [
            775,
            365
          ],
          [
            785,
            355
          ],
          [
            795,
            355
          ],
          [
            795,
            355
          ],
          [
            805,
            345
          ],
          [
            815,
            335
          ],
          [
            825,
            325
          ],
          [
            835,
            315
          ],
          [
            845,
            305
          ],
          [
            855,
            295
          ]
        ],
        "explored_cells": 2024,
        "has_goal": true,
        "goal_position": [
          865,
          285
        ]
      },
      {
        "id": 1021,
        "alive": true,
        "energycost": 8.723337964121718,
        "final_position": [
          545,
          285
        ],
        "trajectory_length": 8,
        "hist_traj": [
          [
            602,
            345
          ],
          [
            605,
            345
          ],
          [
            595,
            335
          ],
          [
            585,
            325
          ],
          [
            575,
            315
          ],
          [
            565,
            305
          ],
          [
            555,
            295
          ],
          [
            545,
            285
          ]
        ],
        "explored_cells": 2276,
        "has_goal": true,
        "goal_position": [
          535,
          275
        ]
      },
      {
        "id": 1022,
        "alive": true,
        "energycost": 8.723337964121718,
        "final_position": [
          545,
          285
        ],
        "trajectory_length": 8,
        "hist_traj": [
          [
            602,
            345
          ],
          [
            605,
            345
          ],
          [
            595,
            335
          ],
          [
            585,
            325
          ],
          [
            575,
            315
          ],
          [
            565,
            305
          ],
          [
            555,
            295
          ],
          [
            545,
            285
          ]
        ],
        "explored_cells": 2547,
        "has_goal": true,
        "goal_position": [
          535,
          275
        ]
      },
      {
        "id": 1023,
        "alive": true,
        "energycost": 0.0,
        "final_position": [
          602,
          345
        ],
        "trajectory_length": 1,
        "hist_traj": [
          [
            602,
            345
          ]
        ],
        "explored_cells": 2953,
        "has_goal": false,
        "goal_position": null
      },
      {
        "id": 1001,
        "alive": false,
        "energycost": 1.2380565898831484,
        "final_position": [
          615,
          345
        ],
        "trajectory_length": 3,
        "hist_traj": [
          [
            602,
            345
          ],
          [
            605,
            345
          ],
          [
            615,
            345
          ]
        ],
        "explored_cells": 396,
        "has_goal": true,
        "goal_position": [
          625,
          345
        ]
      },
      {
        "id": 1002,
        "alive": false,
        "energycost": 1.6522701522562433,
        "final_position": [
          615,
          355
        ],
        "trajectory_length": 3,
        "hist_traj": [
          [
            602,
            345
          ],
          [
            605,
            345
          ],
          [
            615,
            355
          ]
        ],
        "explored_cells": 396,
        "has_goal": true,
        "goal_position": [
          625,
          355
        ]
      },
      {
        "id": 1003,
        "alive": false,
        "energycost": 1.6522701522562433,
        "final_position": [
          615,
          355
        ],
        "trajectory_length": 3,
        "hist_traj": [
          [
            602,
            345
          ],
          [
            605,
            345
          ],
          [
            615,
            355
          ]
        ],
        "explored_cells": 396,
        "has_goal": true,
        "goal_position": [
          625,
          365
        ]
      },
      {
        "id": 1005,
        "alive": false,
        "energycost": 1.2380565898831484,
        "final_position": [
          615,
          345
        ],
        "trajectory_length": 3,
        "hist_traj": [
          [
            602,
            345
          ],
          [
            605,
            345
          ],
          [
            615,
            345
          ]
        ],
        "explored_cells": 396,
        "has_goal": true,
        "goal_position": [
          625,
          345
        ]
      },
      {
        "id": 1008,
        "alive": false,
        "energycost": 1.6522701522562433,
        "final_position": [
          615,
          335
        ],
        "trajectory_length": 3,
        "hist_traj": [
          [
            602,
            345
          ],
          [
            605,
            345
          ],
          [
            615,
            335
          ]
        ],
        "explored_cells": 396,
        "has_goal": true,
        "goal_position": [
          625,
          325
        ]
      },
      {
        "id": 1004,
        "alive": false,
        "energycost": 5.480697277002434,
        "final_position": [
          575,
          385
        ],
        "trajectory_length": 6,
        "hist_traj": [
          [
            602,
            345
          ],
          [
            605,
            345
          ],
          [
            595,
            355
          ],
          [
            585,
            365
          ],
          [
            575,
            375
          ],
          [
            575,
            385
          ]
        ],
        "explored_cells": 445,
        "has_goal": true,
        "goal_position": [
          565,
          395
        ]
      },
      {
        "id": 1000,
        "alive": false,
        "energycost": 6.066483714629339,
        "final_position": [
          585,
          395
        ],
        "trajectory_length": 7,
        "hist_traj": [
          [
            602,
            345
          ],
          [
            605,
            345
          ],
          [
            605,
            355
          ],
          [
            605,
            365
          ],
          [
            595,
            375
          ],
          [
            595,
            385
          ],
          [
            585,
            395
          ]
        ],
        "explored_cells": 448,
        "has_goal": true,
        "goal_position": [
          585,
          405
        ]
      },
      {
        "id": 1009,
        "alive": false,
        "energycost": 5.8949108393755285,
        "final_position": [
          565,
          385
        ],
        "trajectory_length": 6,
        "hist_traj": [
          [
            602,
            345
          ],
          [
            605,
            345
          ],
          [
            595,
            355
          ],
          [
            585,
            365
          ],
          [
            575,
            375
          ],
          [
            565,
            385
          ]
        ],
        "explored_cells": 461,
        "has_goal": true,
        "goal_position": [
          555,
          385
        ]
      },
      {
        "id": 1007,
        "alive": false,
        "energycost": 12.894910839375529,
        "final_position": [
          615,
          285
        ],
        "trajectory_length": 14,
        "hist_traj": [
          [
            602,
            345
          ],
          [
            605,
            345
          ],
          [
            595,
            335
          ],
          [
            585,
            325
          ],
          [
            575,
            315
          ],
          [
            575,
            305
          ],
          [
            565,
            295
          ],
          [
            565,
            285
          ],
          [
            565,
            285
          ],
          [
            575,
            285
          ],
          [
            585,
            285
          ],
          [
            595,
            285
          ],
          [
            605,
            285
          ],
          [
            615,
            285
          ]
        ],
        "explored_cells": 501,
        "has_goal": true,
        "goal_position": [
          625,
          285
        ]
      },
      {
        "id": 1006,
        "alive": false,
        "energycost": 17.55176508886791,
        "final_position": [
          585,
          385
        ],
        "trajectory_length": 17,
        "hist_traj": [
          [
            602,
            345
          ],
          [
            605,
            345
          ],
          [
            595,
            335
          ],
          [
            585,
            325
          ],
          [
            575,
            315
          ],
          [
            565,
            315
          ],
          [
            555,
            305
          ],
          [
            545,
            305
          ],
          [
            545,
            305
          ],
          [
            555,
            315
          ],
          [
            555,
            325
          ],
          [
            565,
            335
          ],
          [
            565,
            345
          ],
          [
            575,
            355
          ],
          [
            575,
            365
          ],
          [
            585,
            375
          ],
          [
            585,
            385
          ]
        ],
        "explored_cells": 528,
        "has_goal": true,
        "goal_position": [
          585,
          395
        ]
      },
      {
        "id": 1011,
        "alive": false,
        "energycost": 35.965978651241,
        "final_position": [
          705,
          175
        ],
        "trajectory_length": 35,
        "hist_traj": [
          [
            602,
            345
          ],
          [
            605,
            345
          ],
          [
            605,
            355
          ],
          [
            605,
            365
          ],
          [
            605,
            375
          ],
          [
            605,
            385
          ],
          [
            615,
            395
          ],
          [
            625,
            395
          ],
          [
            635,
            395
          ],
          [
            645,
            395
          ],
          [
            655,
            395
          ],
          [
            665,
            395
          ],
          [
            675,
            385
          ],
          [
            675,
            375
          ],
          [
            675,
            365
          ],
          [
            685,
            355
          ],
          [
            695,
            345
          ],
          [
            705,
            335
          ],
          [
            715,
            325
          ],
          [
            715,
            315
          ],
          [
            715,
            305
          ],
          [
            715,
            295
          ],
          [
            715,
            285
          ],
          [
            715,
            275
          ],
          [
            715,
            265
          ],
          [
            715,
            255
          ],
          [
            725,
            245
          ],
          [
            725,
            245
          ],
          [
            715,
            235
          ],
          [
            715,
            225
          ],
          [
            715,
            215
          ],
          [
            715,
            205
          ],
          [
            715,
            195
          ],
          [
            715,
            185
          ],
          [
            705,
            175
          ]
        ],
        "explored_cells": 1111,
        "has_goal": true,
        "goal_position": [
          695,
          175
        ]
      },
      {
        "id": 1010,
        "alive": false,
        "energycost": 38.7944057759872,
        "final_position": [
          495,
          385
        ],
        "trajectory_length": 37,
        "hist_traj": [
          [
            602,
            345
          ],
          [
            605,
            345
          ],
          [
            595,
            335
          ],
          [
            585,
            325
          ],
          [
            575,
            315
          ],
          [
            565,
            305
          ],
          [
            555,
            295
          ],
          [
            545,
            285
          ],
          [
            535,
            275
          ],
          [
            525,
            265
          ],
          [
            525,
            255
          ],
          [
            515,
            245
          ],
          [
            515,
            235
          ],
          [
            505,
            225
          ],
          [
            505,
            215
          ],
          [
            495,
            205
          ],
          [
            495,
            195
          ],
          [
            495,
            195
          ],
          [
            495,
            205
          ],
          [
            495,
            215
          ],
          [
            495,
            225
          ],
          [
            495,
            235
          ],
          [
            495,
            245
          ],
          [
            495,
            255
          ],
          [
            495,
            265
          ],
          [
            495,
            275
          ],
          [
            495,
            285
          ],
          [
            495,
            295
          ],
          [
            495,
            305
          ],
          [
            495,
            315
          ],
          [
            495,
            325
          ],
          [
            495,
            335
          ],
          [
            495,
            345
          ],
          [
            495,
            355
          ],
          [
            495,
            365
          ],
          [
            495,
            375
          ],
          [
            495,
            385
          ]
        ],
        "explored_cells": 779,
        "has_goal": true,
        "goal_position": [
          495,
          395
        ]
      },
      {
        "id": 1014,
        "alive": false,
        "energycost": 26.45126002547958,
        "final_position": [
          455,
          145
        ],
        "trajectory_length": 22,
        "hist_traj": [
          [
            602,
            345
          ],
          [
            605,
            345
          ],
          [
            595,
            335
          ],
          [
            585,
            325
          ],
          [
            575,
            315
          ],
          [
            565,
            305
          ],
          [
            555,
            295
          ],
          [
            545,
            285
          ],
          [
            535,
            275
          ],
          [
            525,
            265
          ],
          [
            515,
            255
          ],
          [
            505,
            245
          ],
          [
            505,
            235
          ],
          [
            495,
            225
          ],
          [
            495,
            215
          ],
          [
            485,
            205
          ],
          [
            485,
            195
          ],
          [
            475,
            185
          ],
          [
            475,
            175
          ],
          [
            465,
            165
          ],
          [
            465,
            155
          ],
          [
            455,
            145
          ]
        ],
        "explored_cells": 1212,
        "has_goal": true,
        "goal_position": [
          455,
          135
        ]
      },
      {
        "id": 1013,
        "alive": false,
        "energycost": 56.62283290073336,
        "final_position": [
          515,
          195
        ],
        "trajectory_length": 54,
        "hist_traj": [
          [
            602,
            345
          ],
          [
            605,
            345
          ],
          [
            605,
            355
          ],
          [
            605,
            365
          ],
          [
            605,
            375
          ],
          [
            605,
            385
          ],
          [
            615,
            395
          ],
          [
            625,
            395
          ],
          [
            635,
            395
          ],
          [
            645,
            395
          ],
          [
            655,
            395
          ],
          [
            665,
            395
          ],
          [
            675,
            395
          ],
          [
            685,
            395
          ],
          [
            695,
            395
          ],
          [
            705,
            395
          ],
          [
            715,
            395
          ],
          [
            725,
            395
          ],
          [
            735,
            395
          ],
          [
            745,
            405
          ],
          [
            745,
            405
          ],
          [
            735,
            395
          ],
          [
            725,
            395
          ],
          [
            715,
            395
          ],
          [
            705,
            395
          ],
          [
            695,
            395
          ],
          [
            685,
            395
          ],
          [
            675,
            395
          ],
          [
            665,
            395
          ],
          [
            655,
            395
          ],
          [
            645,
            395
          ],
          [
            635,
            395
          ],
          [
            625,
            395
          ],
          [
            615,
            395
          ],
          [
            605,
            385
          ],
          [
            595,
            375
          ],
          [
            595,
            365
          ],
          [
            585,
            355
          ],
          [
            585,
            345
          ],
          [
            585,
            335
          ],
          [
            575,
            325
          ],
          [
            575,
            315
          ],
          [
            565,
            305
          ],
          [
            565,
            295
          ],
          [
            555,
            285
          ],
          [
            555,
            275
          ],
          [
            545,
            265
          ],
          [
            545,
            255
          ],
          [
            535,
            245
          ],
          [
            535,
            235
          ],
          [
            535,
            225
          ],
          [
            525,
            215
          ],
          [
            525,
            205
          ],
          [
            515,
            195
          ]
        ],
        "explored_cells": 1172,
        "has_goal": true,
        "goal_position": [
          515,
          185
        ]
      },
      {
        "id": 1012,
        "alive": false,
        "energycost": 77.5933956492105,
        "final_position": [
          805,
          185
        ],
        "trajectory_length": 71,
        "hist_traj": [
          [
            602,
            345
          ],
          [
            605,
            345
          ],
          [
            595,
            355
          ],
          [
            585,
            365
          ],
          [
            575,
            375
          ],
          [
            565,
            375
          ],
          [
            555,
            375
          ],
          [
            545,
            375
          ],
          [
            535,
            375
          ],
          [
            525,
            375
          ],
          [
            515,
            375
          ],
          [
            505,
            375
          ],
          [
            495,
            375
          ],
          [
            485,
            385
          ],
          [
            475,
            395
          ],
          [
            475,
            405
          ],
          [
            465,
            415
          ],
          [
            465,
            425
          ],
          [
            455,
            435
          ],
          [
            455,
            445
          ],
          [
            445,
            455
          ],
          [
            445,
            465
          ],
          [
            445,
            465
          ],
          [
            455,
            455
          ],
          [
            465,
            445
          ],
          [
            475,
            435
          ],
          [
            485,
            425
          ],
          [
            495,
            415
          ],
          [
            505,
            405
          ],
          [
            515,
            405
          ],
          [
            525,
            405
          ],
          [
            535,
            405
          ],
          [
            545,
            405
          ],
          [
            555,
            405
          ],
          [
            565,
            405
          ],
          [
            575,
            405
          ],
          [
            585,
            405
          ],
          [
            595,
            395
          ],
          [
            605,
            395
          ],
          [
            615,
            395
          ],
          [
            625,
            395
          ],
          [
            635,
            395
          ],
          [
            645,
            395
          ],
          [
            655,
            395
          ],
          [
            665,
            395
          ],
          [
            675,
            385
          ],
          [
            675,
            375
          ],
          [
            685,
            365
          ],
          [
            685,
            355
          ],
          [
            695,
            345
          ],
          [
            705,
            335
          ],
          [
            715,
            325
          ],
          [
            715,
            315
          ],
          [
            715,
            305
          ],
          [
            715,
            295
          ],
          [
            715,
            285
          ],
          [
            725,
            275
          ],
          [
            725,
            265
          ],
          [
            735,
            255
          ],
          [
            735,
            245
          ],
          [
            745,
            235
          ],
          [
            745,
            225
          ],
          [
            755,
            215
          ],
          [
            755,
            205
          ],
          [
            755,
            195
          ],
          [
            765,
            185
          ],
          [
            765,
            185
          ],
          [
            775,
            185
          ],
          [
            785,
            185
          ],
          [
            795,
            185
          ],
          [
            805,
            185
          ]
        ],
        "explored_cells": 1307,
        "has_goal": true,
        "goal_position": [
          815,
          185
        ]
      },
      {
        "id": 1017,
        "alive": false,
        "energycost": 28.7944057759872,
        "final_position": [
          695,
          125
        ],
        "trajectory_length": 26,
        "hist_traj": [
          [
            602,
            345
          ],
          [
            605,
            345
          ],
          [
            595,
            335
          ],
          [
            585,
            325
          ],
          [
            585,
            315
          ],
          [
            585,
            305
          ],
          [
            585,
            295
          ],
          [
            585,
            285
          ],
          [
            585,
            275
          ],
          [
            585,
            265
          ],
          [
            585,
            255
          ],
          [
            585,
            245
          ],
          [
            585,
            235
          ],
          [
            585,
            225
          ],
          [
            585,
            215
          ],
          [
            595,
            205
          ],
          [
            605,
            195
          ],
          [
            615,
            185
          ],
          [
            625,
            175
          ],
          [
            635,
            165
          ],
          [
            645,
            155
          ],
          [
            655,
            145
          ],
          [
            665,
            145
          ],
          [
            675,
            135
          ],
          [
            685,
            135
          ],
          [
            695,
            125
          ]
        ],
        "explored_cells": 1773,
        "has_goal": true,
        "goal_position": [
          705,
          125
        ]
      },
      {
        "id": 1018,
        "alive": false,
        "energycost": 33.10811427497197,
        "final_position": [
          475,
          575
        ],
        "trajectory_length": 28,
        "hist_traj": [
          [
            602,
            345
          ],
          [
            605,
            345
          ],
          [
            595,
            355
          ],
          [
            595,
            365
          ],
          [
            595,
            375
          ],
          [
            595,
            385
          ],
          [
            595,
            395
          ],
          [
            585,
            405
          ],
          [
            575,
            415
          ],
          [
            565,
            425
          ],
          [
            555,
            435
          ],
          [
            545,
            445
          ],
          [
            535,
            455
          ],
          [
            525,
            455
          ],
          [
            515,
            455
          ],
          [
            505,
            465
          ],
          [
            495,
            475
          ],
          [
            485,
            485
          ],
          [
            475,
            495
          ],
          [
            465,
            505
          ],
          [
            455,
            515
          ],
          [
            445,
            525
          ],
          [
            435,
            535
          ],
          [
            435,
            535
          ],
          [
            445,
            545
          ],
          [
            455,
            555
          ],
          [
            465,
            565
          ],
          [
            475,
            575
          ]
        ],
        "explored_cells": 1928,
        "has_goal": true,
        "goal_position": [
          485,
          585
        ]
      }
    ],
    "large_agents": [
      {
        "id": 2,
        "alive": true,
        "energycost": 276.8680321655528,
        "final_position": [
          875,
          465
        ],
        "trajectory_length": 121,
        "hist_traj": [
          [
            602,
            345
          ],
          [
            605,
            345
          ],
          [
            595,
            345
          ],
          [
            585,
            345
          ],
          [
            575,
            345
          ],
          [
            565,
            355
          ],
          [
            555,
            355
          ],
          [
            545,
            355
          ],
          [
            535,
            365
          ],
          [
            535,
            365
          ],
          [
            545,
            375
          ],
          [
            555,
            375
          ],
          [
            565,
            375
          ],
          [
            575,
            375
          ],
          [
            585,
            375
          ],
          [
            595,
            385
          ],
          [
            605,
            395
          ],
          [
            615,
            405
          ],
          [
            615,
            415
          ],
          [
            625,
            425
          ],
          [
            625,
            435
          ],
          [
            635,
            445
          ],
          [
            635,
            455
          ],
          [
            645,
            465
          ],
          [
            645,
            475
          ],
          [
            645,
            485
          ],
          [
            655,
            495
          ],
          [
            655,
            495
          ],
          [
            655,
            485
          ],
          [
            655,
            475
          ],
          [
            655,
            465
          ],
          [
            655,
            455
          ],
          [
            655,
            445
          ],
          [
            655,
            435
          ],
          [
            645,
            425
          ],
          [
            635,
            415
          ],
          [
            625,
            405
          ],
          [
            615,
            395
          ],
          [
            605,
            385
          ],
          [
            605,
            375
          ],
          [
            605,
            365
          ],
          [
            605,
            355
          ],
          [
            605,
            345
          ],
          [
            595,
            335
          ],
          [
            585,
            325
          ],
          [
            585,
            315
          ],
          [
            585,
            305
          ],
          [
            585,
            295
          ],
          [
            585,
            285
          ],
          [
            585,
            275
          ],
          [
            575,
            265
          ],
          [
            565,
            255
          ],
          [
            555,
            245
          ],
          [
            545,
            235
          ],
          [
            535,
            225
          ],
          [
            525,
            215
          ],
          [
            515,
            205
          ],
          [
            505,
            195
          ],
          [
            505,
            185
          ],
          [
            505,
            175
          ],
          [
            515,
            165
          ],
          [
            515,
            155
          ],
          [
            515,
            145
          ],
          [
            525,
            135
          ],
          [
            525,
            135
          ],
          [
            525,
            145
          ],
          [
            525,
            155
          ],
          [
            525,
            165
          ],
          [
            515,
            175
          ],
          [
            505,
            185
          ],
          [
            505,
            195
          ],
          [
            515,
            205
          ],
          [
            525,
            215
          ],
          [
            535,
            225
          ],
          [
            545,
            235
          ],
          [
            555,
            245
          ],
          [
            565,
            255
          ],
          [
            575,
            265
          ],
          [
            585,
            275
          ],
          [
            585,
            285
          ],
          [
            585,
            295
          ],
          [
            585,
            305
          ],
          [
            585,
            315
          ],
          [
            585,
            325
          ],
          [
            595,
            335
          ],
          [
            605,
            345
          ],
          [
            605,
            355
          ],
          [
            605,
            365
          ],
          [
            605,
            375
          ],
          [
            605,
            385
          ],
          [
            615,
            395
          ],
          [
            625,
            405
          ],
          [
            635,
            415
          ],
          [
            645,
            425
          ],
          [
            655,
            435
          ],
          [
            665,
            445
          ],
          [
            675,
            445
          ],
          [
            685,
            455
          ],
          [
            695,
            455
          ],
          [
            705,
            465
          ],
          [
            715,
            465
          ],
          [
            725,
            475
          ],
          [
            735,
            475
          ],
          [
            745,
            475
          ],
          [
            755,
            485
          ],
          [
            765,
            485
          ],
          [
            775,
            495
          ],
          [
            785,
            495
          ],
          [
            795,
            505
          ],
          [
            805,
            505
          ],
          [
            815,
            515
          ],
          [
            825,
            515
          ],
          [
            835,
            515
          ],
          [
            845,
            525
          ],
          [
            845,
            525
          ],
          [
            855,
            515
          ],
          [
            855,
            505
          ],
          [
            865,
            495
          ],
          [
            865,
            485
          ],
          [
            875,
            475
          ],
          [
            875,
            465
          ]
        ],
        "known_cells": 3201,
        "total_cells": 7000,
        "known_percentage": 45.72857142857143,
        "son_agents": [
          1015,
          1016,
          1023
        ]
      },
      {
        "id": 0,
        "alive": false,
        "energycost": 3.3045403045124866,
        "final_position": [
          615,
          335
        ],
        "trajectory_length": 3,
        "hist_traj": [
          [
            602,
            345
          ],
          [
            605,
            345
          ],
          [
            615,
            335
          ]
        ],
        "known_cells": 396,
        "total_cells": 7000,
        "known_percentage": 5.6571428571428575,
        "son_agents": [
          1000,
          1001,
          1002
        ]
      },
      {
        "id": 1,
        "alive": false,
        "energycost": 210.44162529435994,
        "final_position": [
          825,
          215
        ],
        "trajectory_length": 93,
        "hist_traj": [
          [
            602,
            345
          ],
          [
            605,
            345
          ],
          [
            595,
            345
          ],
          [
            585,
            345
          ],
          [
            575,
            345
          ],
          [
            565,
            345
          ],
          [
            555,
            345
          ],
          [
            545,
            345
          ],
          [
            535,
            345
          ],
          [
            535,
            345
          ],
          [
            535,
            335
          ],
          [
            525,
            325
          ],
          [
            525,
            315
          ],
          [
            525,
            305
          ],
          [
            515,
            295
          ],
          [
            515,
            285
          ],
          [
            505,
            275
          ],
          [
            505,
            265
          ],
          [
            495,
            255
          ],
          [
            495,
            245
          ],
          [
            485,
            235
          ],
          [
            485,
            225
          ],
          [
            485,
            215
          ],
          [
            475,
            205
          ],
          [
            475,
            205
          ],
          [
            485,
            215
          ],
          [
            495,
            225
          ],
          [
            505,
            235
          ],
          [
            515,
            245
          ],
          [
            525,
            255
          ],
          [
            535,
            265
          ],
          [
            545,
            275
          ],
          [
            555,
            285
          ],
          [
            565,
            295
          ],
          [
            575,
            305
          ],
          [
            585,
            315
          ],
          [
            585,
            325
          ],
          [
            595,
            335
          ],
          [
            605,
            345
          ],
          [
            605,
            355
          ],
          [
            605,
            365
          ],
          [
            605,
            375
          ],
          [
            605,
            385
          ],
          [
            615,
            395
          ],
          [
            625,
            405
          ],
          [
            635,
            415
          ],
          [
            645,
            425
          ],
          [
            645,
            435
          ],
          [
            645,
            445
          ],
          [
            655,
            455
          ],
          [
            655,
            465
          ],
          [
            665,
            475
          ],
          [
            665,
            485
          ],
          [
            675,
            495
          ],
          [
            675,
            505
          ],
          [
            685,
            515
          ],
          [
            685,
            525
          ],
          [
            685,
            535
          ],
          [
            695,
            545
          ],
          [
            695,
            545
          ],
          [
            695,
            535
          ],
          [
            695,
            525
          ],
          [
            695,
            515
          ],
          [
            695,
            505
          ],
          [
            695,
            495
          ],
          [
            705,
            485
          ],
          [
            705,
            475
          ],
          [
            715,
            465
          ],
          [
            715,
            455
          ],
          [
            725,
            445
          ],
          [
            725,
            435
          ],
          [
            725,
            425
          ],
          [
            735,
            415
          ],
          [
            735,
            405
          ],
          [
            745,
            395
          ],
          [
            745,
            385
          ],
          [
            755,
            375
          ],
          [
            755,
            365
          ],
          [
            765,
            355
          ],
          [
            765,
            345
          ],
          [
            775,
            335
          ],
          [
            775,
            325
          ],
          [
            775,
            315
          ],
          [
            785,
            305
          ],
          [
            785,
            295
          ],
          [
            795,
            285
          ],
          [
            795,
            275
          ],
          [
            805,
            265
          ],
          [
            805,
            255
          ],
          [
            815,
            245
          ],
          [
            815,
            235
          ],
          [
            815,
            225
          ],
          [
            825,
            215
          ]
        ],
        "known_cells": 2739,
        "total_cells": 7000,
        "known_percentage": 39.128571428571426,
        "son_agents": [
          1019,
          1020,
          1021,
          1022
        ]
      }
    ]
  }
}